i18n_fields/__init__.py
i18n_fields/admin.py
i18n_fields/apps.py
i18n_fields/descriptor.py
i18n_fields/expressions.py
i18n_fields/forms.py
i18n_fields/lookups.py
i18n_fields/mixins.py
i18n_fields/py.typed
i18n_fields/settings.py
i18n_fields/util.py
i18n_fields/value.py
i18n_fields/widgets.py
i18n_fields/drf/__init__.py
i18n_fields/drf/serializer_fields.py
i18n_fields/drf/serializers.py
i18n_fields/fields/__init__.py
i18n_fields/fields/boolean_field.py
i18n_fields/fields/char_field.py
i18n_fields/fields/field.py
i18n_fields/fields/file_field.py
i18n_fields/fields/float_field.py
i18n_fields/fields/integer_field.py
i18n_fields/fields/text_field.py
i18n_fields/fields/uniqueslug_field.py
i18n_fields/static/i18n_fields/i18n-fields-admin.css
i18n_fields/static/i18n_fields/i18n-fields-admin.js
i18n_fields/templates/i18n_fields/multiwidget.html
i18n_fields/templates/i18n_fields/admin/widget_dropdown.html
i18n_fields/templates/i18n_fields/admin/widget_tabs.html
django_i18n_fields-1.1.1.dist-info/METADATA
django_i18n_fields-1.1.1.dist-info/WHEEL
django_i18n_fields-1.1.1.dist-info/licenses/AUTHORS.rst
django_i18n_fields-1.1.1.dist-info/licenses/LICENSE
django_i18n_fields-1.1.1.dist-info/RECORD
